d_serialize/__init__.py
d_serialize/d_serialize.py
d_serialize-1.0.6.dist-info/LICENSE
d_serialize-1.0.6.dist-info/METADATA
d_serialize-1.0.6.dist-info/WHEEL
d_serialize-1.0.6.dist-info/top_level.txt
d_serialize-1.0.6.dist-info/RECORD
