Metadata-Version: 2.1
Name: d-serialize
Version: 1.0.6
Summary: Universal Python serializer
Home-page: https://github.com/Martlark/d_serialize
Author: Andrew Rowe
Author-email: rowe.andrew.d@gmail.com
License: Apache Software License
Download-URL: https://github.com/Martlark/d_serialize/archive/1.0.6.tar.gz
Keywords: serialize json convert dict
Platform: UNKNOWN
Classifier: Development Status :: 5 - Production/Stable
Classifier: Intended Audience :: Developers
Classifier: Topic :: Software Development :: Libraries :: Python Modules
Classifier: License :: OSI Approved :: Apache Software License
Classifier: Programming Language :: Python
Classifier: Programming Language :: Python :: 3
Classifier: Programming Language :: Python :: 3.5
Classifier: Programming Language :: Python :: 3.6
Classifier: Programming Language :: Python :: 3.7
Classifier: Programming Language :: Python :: 3.8
Classifier: Programming Language :: Python :: 3.9
Classifier: Programming Language :: Python :: 3.10
Classifier: Programming Language :: Python :: 3.11
Classifier: Operating System :: POSIX
Classifier: Operating System :: MacOS
Classifier: Operating System :: Unix
Classifier: Operating System :: Microsoft :: Windows
License-File: LICENSE
